udotu.py
udotu-0.0.1.dist-info/WHEEL
udotu-0.0.1.dist-info/METADATA
udotu-0.0.1.dist-info/RECORD
