Metadata-Version: 2.1
Name: udotu
Version: 0.0.1
Summary: print debugging for a more civilized age
Author: Jon Skulski
Author-email: jskulski@gmail.com
Requires-Python: >=3.7,<4.0
Classifier: Programming Language :: Python :: 3
Classifier: Programming Language :: Python :: 3.7
Classifier: Programming Language :: Python :: 3.8
Classifier: Programming Language :: Python :: 3.9
